[
    {
        "id": 1582738697275226,
        "idprod": 1582746008280805,
        "nomeprod": "ragdoll",
        "precoprod": "78",
        "descprod": "",
        "imgprod": "..\/img\/1582738697275226.jpg"
    },
    {
        "id": 1582738697275226,
        "idprod": 1582746028361388,
        "nomeprod": "persa",
        "precoprod": "12",
        "descprod": "",
        "imgprod": "..\/img\/1.5827460082808E+15.jpg"
    },
    {
        "id": 1582738668094461,
        "idprod": 1582746079529450,
        "nomeprod": "frajolinha",
        "precoprod": "1",
        "descprod": "",
        "imgprod": "..\/img\/1582738668094461.jpg"
    },
    {
        "id": 1582738668094461,
        "idprod": 1582746609290635,
        "nomeprod": "tabby grey maine coon",
        "precoprod": "3",
        "descprod": "",
        "imgprod": "..\/img\/1.5827464627531E+15.jpg"
    },
    {
        "id": 1582738709483524,
        "idprod": 1582747072633214,
        "nomeprod": "orange tabby argentino",
        "precoprod": "6",
        "descprod": "",
        "imgprod": "..\/img\/1582738709483524.jpg"
    },
    {
        "id": 1582738709483524,
        "idprod": 1582747172217234,
        "nomeprod": "orange and gris tortoiseshell argentina",
        "precoprod": "2",
        "descprod": "",
        "imgprod": "..\/img\/1.5827470726332E+15.jpg"
    }
]